stock_crawler_utils/__init__.py
stock_crawler_utils/exceptions.py
stock_crawler_utils/decorators/__init__.py
stock_crawler_utils/decorators/consumer.py
stock_crawler_utils/decorators/publisher.py
stock_crawler_utils/ftp_uploader/__init__.py
stock_crawler_utils/ftp_uploader/ftp_uploader.py
stock_crawler_utils/shortcuts/__init__.py
stock_crawler_utils/shortcuts/shortcuts.py
stock_crawler_utils/tasks/__init__.py
stock_crawler_utils/tasks/delayed_tasks.py
stock_crawler_utils/xpath/__init__.py
stock_crawler_utils/xpath/xpath.py
stock_crawler_utils-0.0.11.dist-info/LICENSE.txt
stock_crawler_utils-0.0.11.dist-info/METADATA
stock_crawler_utils-0.0.11.dist-info/WHEEL
stock_crawler_utils-0.0.11.dist-info/top_level.txt
stock_crawler_utils-0.0.11.dist-info/RECORD
